asmc/__init__.py
statgentools/__init__.py
statgentools-0.2.dist-info/COPYING
statgentools-0.2.dist-info/LICENSE
statgentools-0.2.dist-info/METADATA
statgentools-0.2.dist-info/WHEEL
statgentools-0.2.dist-info/top_level.txt
statgentools-0.2.dist-info/RECORD
