Metadata-Version: 2.1
Name: statgentools
Version: 0.2
Summary: An ecosystem of tools for statistical genetics
Home-page: UNKNOWN
Author: statgentools team
License: UNKNOWN
Platform: UNKNOWN
Classifier: Programming Language :: Python :: 3
Classifier: License :: OSI Approved :: GNU General Public License v3 (GPLv3)
Requires-Python: >=3.6
License-File: LICENSE
License-File: COPYING
Provides-Extra: pypi
Requires-Dist: build ; extra == 'pypi'
Requires-Dist: twine ; extra == 'pypi'
